{
    "key": "group_6602a56658b9d",
    "title": "Home Page Template",
    "fields": [
        {
            "key": "field_6602a56764c41",
            "label": "Hero Title",
            "name": "hero_title",
            "aria-label": "",
            "type": "text",
            "instructions": "",
            "required": 0,
            "conditional_logic": 0,
            "wrapper": {
                "width": "",
                "class": "",
                "id": ""
            },
            "default_value": "",
            "maxlength": "",
            "placeholder": "",
            "prepend": "",
            "append": ""
        },
        {
            "key": "field_6602a890af34c",
            "label": "Hero Subtitle",
            "name": "hero_subtitle",
            "aria-label": "",
            "type": "textarea",
            "instructions": "",
            "required": 0,
            "conditional_logic": 0,
            "wrapper": {
                "width": "",
                "class": "",
                "id": ""
            },
            "default_value": "",
            "maxlength": "",
            "rows": 4,
            "placeholder": "",
            "new_lines": "br"
        },
        {
            "key": "field_6603e4dee987e",
            "label": "About Us",
            "name": "about_us",
            "aria-label": "",
            "type": "text",
            "instructions": "",
            "required": 0,
            "conditional_logic": 0,
            "wrapper": {
                "width": "",
                "class": "",
                "id": ""
            },
            "default_value": "",
            "maxlength": "",
            "placeholder": "",
            "prepend": "",
            "append": ""
        },
        {
            "key": "field_6603e4fce987f",
            "label": "About Us text",
            "name": "about_us_text",
            "aria-label": "",
            "type": "textarea",
            "instructions": "",
            "required": 0,
            "conditional_logic": 0,
            "wrapper": {
                "width": "",
                "class": "",
                "id": ""
            },
            "default_value": "Lorem ipsum dolor sit amet consectetur adipisicing elit. Dolor amet recusandae ratione, voluptates sequi deleniti nostrum excepturi cum ea et ut distinctio! Eum at iure, doloremque reiciendis ex sit autem.Lorem ipsum dolor sit amet consectetur adipisicing elit. Dolor amet recusandae ratione, voluptates sequi deleniti nostrum excepturi cum ea et ut distinctio!",
            "maxlength": "",
            "rows": 4,
            "placeholder": "",
            "new_lines": "br"
        }
    ],
    "location": [
        [
            {
                "param": "page_template",
                "operator": "==",
                "value": "template-home.php"
            }
        ]
    ],
    "menu_order": 0,
    "position": "normal",
    "style": "default",
    "label_placement": "top",
    "instruction_placement": "label",
    "hide_on_screen": [
        "the_content"
    ],
    "active": true,
    "description": "",
    "show_in_rest": 0,
    "modified": 1711531803
}
